django_auth_irwin-1.0.0.dist-info/licenses/LICENSE
package_phonecode/__init__.py
package_phonecode/apps.py
package_phonecode/data.py
package_phonecode/forms.py
package_phonecode/urls.py
package_phonecode/views.py
package_phonecode/templates/package_phonecode/index.html
test1/__init__.py
test1/asgi.py
test1/settings.py
test1/urls.py
test1/wsgi.py
django_auth_irwin-1.0.0.dist-info/METADATA
django_auth_irwin-1.0.0.dist-info/WHEEL
django_auth_irwin-1.0.0.dist-info/top_level.txt
django_auth_irwin-1.0.0.dist-info/RECORD
